monetary/__init__.py
monetary/main.py
monetary-1.0.3.dist-info/METADATA
monetary-1.0.3.dist-info/WHEEL
monetary-1.0.3.dist-info/top_level.txt
monetary-1.0.3.dist-info/RECORD
